{
  "title": "LinkedIn Pinpoint Game Tips & Strategies",
  "source": "https://pinpointanswertoday.online/",
  "description": "Comprehensive tips and strategies for solving the LinkedIn Pinpoint daily word puzzle game. Visit https://pinpointanswertoday.online/ for daily answers.",
  "strategies": [
    {
      "strategy": "Start with category clues",
      "description": "Focus on the category hint provided at the top. It narrows down the word space significantly.",
      "difficulty_reduction": "high"
    },
    {
      "strategy": "Letter frequency analysis",
      "description": "Common English letters like E, T, A, O, I, N appear most frequently. Guess these first.",
      "difficulty_reduction": "medium"
    },
    {
      "strategy": "Use process of elimination",
      "description": "Each wrong guess eliminates possibilities. Track eliminated letters systematically.",
      "difficulty_reduction": "medium"
    },
    {
      "strategy": "Look for word patterns",
      "description": "Double letters, common suffixes (-ing, -tion, -ness), and prefixes (un-, re-, pre-) are helpful patterns.",
      "difficulty_reduction": "high"
    },
    {
      "strategy": "Consider LinkedIn-specific vocabulary",
      "description": "Pinpoint often uses business and professional terms. Think corporate jargon, job titles, and industry terms.",
      "difficulty_reduction": "high"
    },
    {
      "strategy": "Daily practice builds pattern recognition",
      "description": "Regular players develop intuition for common word structures and categories used in the game.",
      "difficulty_reduction": "low"
    }
  ],
  "common_categories": [
    "Business & Finance",
    "Technology & Innovation",
    "Leadership & Management",
    "Career Development",
    "Industry Terminology",
    "Soft Skills & Communication"
  ],
  "resources": {
    "daily_answers": "https://pinpointanswertoday.online/",
    "hints_and_tips": "https://pinpointanswertoday.online/",
    "puzzle_archive": "https://pinpointanswertoday.online/"
  },
  "credits": "Tips compiled from the community at https://pinpointanswertoday.online/ - Your daily source for LinkedIn Pinpoint answers and hints."
}